rs2wapy/__init__.py
rs2wapy/_version.py
rs2wapy/rs2wapy.py
rs2wapy/adapters/__init__.py
rs2wapy/adapters/adapters.py
rs2wapy/epicgamesstore/__init__.py
rs2wapy/epicgamesstore/epicgamesstore.py
rs2wapy/models/__init__.py
rs2wapy/models/models.py
rs2wapy/parsing/__init__.py
rs2wapy/parsing/parsing.py
rs2wapy/steam/__init__.py
rs2wapy/steam/steam.py
rs2wapy-0.7.1.dist-info/METADATA
rs2wapy-0.7.1.dist-info/WHEEL
rs2wapy-0.7.1.dist-info/licenses/LICENSE
rs2wapy-0.7.1.dist-info/RECORD
