Metadata-Version: 2.4
Name: rs2wapy
Version: 0.7.1
Summary: Rising Storm 2: Vietnam WebAdmin Python Interface
Project-URL: Documentation, https://github.com/tuokri/rs2wapy#readme
Project-URL: Issues, https://github.com/tuokri/rs2wapy/issues
Project-URL: Source, https://github.com/tuokri/rs2wapy
Author-email: Tuomo Kriikkula <tuokri@tuta.io>
License-File: LICENSE
Keywords: automation webadmin ue3 rcon
Classifier: License :: OSI Approved :: MIT License
Classifier: Operating System :: OS Independent
Classifier: Programming Language :: Python
Classifier: Programming Language :: Python :: 3.9
Classifier: Programming Language :: Python :: 3.10
Classifier: Programming Language :: Python :: 3.11
Classifier: Programming Language :: Python :: 3.12
Classifier: Programming Language :: Python :: 3.13
Classifier: Programming Language :: Python :: Implementation :: CPython
Classifier: Programming Language :: Python :: Implementation :: PyPy
Requires-Python: >=3.9
Requires-Dist: beautifulsoup4==4.13.4
Requires-Dist: logbook==1.8.2
Requires-Dist: pycurl==7.45.6
Requires-Dist: regex==2024.11.6
Requires-Dist: requests==2.32.4
Requires-Dist: soupsieve==2.7
Requires-Dist: steam==1.4.4
Provides-Extra: dev
Requires-Dist: hatch; extra == 'dev'
Requires-Dist: mypy; extra == 'dev'
Requires-Dist: ruff; extra == 'dev'
